simplechinese/__init__.py
simplechinese/conversion.py
simplechinese/generation.py
simplechinese/nlp.py
simplechinese/pinyin.py
simplechinese/preprocessing.py
simplechinese/representation.py
simplechinese/visualization.py
simplechinese/data/all_weights_64.npy
simplechinese/data/all_words.pickle
simplechinese/data/chinese_names.pickle
simplechinese/data/english_names_mini.pickle
simplechinese/data/names.pickle
simplechinese/data/stopwords.txt
simplechinese/data/vocab.txt
simplechinese-0.2.15.dist-info/LICENSE
simplechinese-0.2.15.dist-info/METADATA
simplechinese-0.2.15.dist-info/WHEEL
simplechinese-0.2.15.dist-info/top_level.txt
simplechinese-0.2.15.dist-info/RECORD
